ensmallen-0.8.100.dist-info/METADATA
ensmallen-0.8.100.dist-info/RECORD
ensmallen-0.8.100.dist-info/WHEEL
ensmallen/__init__.py
ensmallen/datasets/__init__.py
ensmallen/datasets/freebase.json.gz
ensmallen/datasets/freebase.py
ensmallen/datasets/get_dataset.py
ensmallen/datasets/get_graph_okapi_tfidf_weighted_textual_embedding.py
ensmallen/datasets/get_kgx_okapi_tfidf_weighted_textual_embedding.py
ensmallen/datasets/get_okapi_tfidf_weighted_textual_embedding.py
ensmallen/datasets/get_string_okapi_tfidf_weighted_textual_embedding.py
ensmallen/datasets/get_wikipedia_tfidf_weighted_textual_embedding.py
ensmallen/datasets/graph_retrieval.py
ensmallen/datasets/harvard.json.gz
ensmallen/datasets/harvard.py
ensmallen/datasets/hetionet.json.gz
ensmallen/datasets/hetionet.py
ensmallen/datasets/jax.json.gz
ensmallen/datasets/jax.py
ensmallen/datasets/kghub.json.gz
ensmallen/datasets/kghub.py
ensmallen/datasets/kgobo.json.gz
ensmallen/datasets/kgobo.py
ensmallen/datasets/linqs.json.gz
ensmallen/datasets/linqs.py
ensmallen/datasets/monarchinitiative.json.gz
ensmallen/datasets/monarchinitiative.py
ensmallen/datasets/networkrepository.json.gz
ensmallen/datasets/networkrepository.py
ensmallen/datasets/pheknowlatorkg.json.gz
ensmallen/datasets/pheknowlatorkg.py
ensmallen/datasets/pubmed.json.gz
ensmallen/datasets/pubmed.py
ensmallen/datasets/string.json.gz
ensmallen/datasets/string.py
ensmallen/datasets/wikidata.json.gz
ensmallen/datasets/wikidata.py
ensmallen/datasets/wikipedia.json.gz
ensmallen/datasets/wikipedia.py
ensmallen/datasets/wikipedia_graph_retrieval.py
ensmallen/datasets/yue.json.gz
ensmallen/datasets/yue.py
ensmallen/datasets/zenodo.json.gz
ensmallen/datasets/zenodo.py
ensmallen/ensmallen_core2.abi3.so
ensmallen/ensmallen_haswell.abi3.so
