Metadata-Version: 2.1
Name: ensmallen
Version: 0.8.100
Requires-Dist: toml~=0.10.0
Requires-Dist: downloaders>=1.0.15
Requires-Dist: compress_json>=1.0.7
Requires-Dist: userinput>=1.0.19
Requires-Dist: cache_decorator>=2.1.11
Requires-Dist: bioregistry>=0.5.65
Requires-Dist: tqdm
Requires-Dist: pandas
Requires-Dist: py-cpuinfo
Requires-Dist: environments_utils>=1.0.13
Summary: 🍇 Ensmallen is the Rust/Python high-performance graph processing submodule of the GRAPE library.
Keywords: python,rust,graph,random,walk
Author: Luca Cappelletti <cappelletti.luca94@gmail.com>, Tommaso Fontana <tommaso.fontana.96@gmail.com>
Author-email: Luca Cappelletti <cappelletti.luca94@gmail.com>, Tommaso Fontana <tommaso.fontana.96@gmail.com>
License: MIT
Requires-Python: >=3.7
